[
  {
    "product_id": "IN_STOCKS_INDS03126",
    "name": "Jagran Prakashan Ltd",
    "clicks": 11,
    "users": 5,
    "current_index": "56.79",
    "momentum_score": "533.99",
    "velocity_score": "21.80",
    "trend_direction": "ACCELERATING",
    "composite_trend_score": 236.37,
    "trend_rank": 1,
    "trend_window": "4 Hours",
    "trending_at": "2025-10-27 04:00:00+00:00",
    "inserted_at": "2025-10-27 12:31:10.954745+00:00"
  },
  {
    "product_id": "IN_STOCKS_INDS04291",
    "name": "Triton Corp. Ltd",
    "clicks": 11,
    "users": 7,
    "current_index": "47.48",
    "momentum_score": "205.46",
    "velocity_score": "11.70",
    "trend_direction": "ACCELERATING",
    "composite_trend_score": 163.4,
    "trend_rank": 2,
    "trend_window": "4 Hours",
    "trending_at": "2025-10-27 04:00:00+00:00",
    "inserted_at": "2025-10-27 12:31:10.954745+00:00"
  },
  {
    "product_id": "IN_STOCKS_INDS20619",
    "name": "Nippon India ETF Nifty Next 50 Junior BeES",
    "clicks": 17,
    "users": 12,
    "current_index": "37.96",
    "momentum_score": "309.14",
    "velocity_score": "11.33",
    "trend_direction": "ACCELERATING",
    "composite_trend_score": 100.47,
    "trend_rank": 3,
    "trend_window": "4 Hours",
    "trending_at": "2025-10-27 04:00:00+00:00",
    "inserted_at": "2025-10-27 12:31:10.954745+00:00"
  },
  {
    "product_id": "IN_STOCKS_INDS10453",
    "name": "IRB InvIT Fund",
    "clicks": 29,
    "users": 20,
    "current_index": "38.68",
    "momentum_score": "566.44",
    "velocity_score": "16.40",
    "trend_direction": "ACCELERATING",
    "composite_trend_score": 100.28,
    "trend_rank": 4,
    "trend_window": "4 Hours",
    "trending_at": "2025-10-27 04:00:00+00:00",
    "inserted_at": "2025-10-27 12:31:10.954745+00:00"
  },
  {
    "product_id": "IN_STOCKS_INDS38787",
    "name": "TechD Cybersecurity Ltd",
    "clicks": 12,
    "users": 9,
    "current_index": "35.26",
    "momentum_score": "379.47",
    "velocity_score": "-17.24",
    "trend_direction": "RISING",
    "composite_trend_score": 80.81,
    "trend_rank": 5,
    "trend_window": "4 Hours",
    "trending_at": "2025-10-27 04:00:00+00:00",
    "inserted_at": "2025-10-27 12:31:10.954745+00:00"
  }
]